setup.py
robotframework_run_keyword_async.egg-info/PKG-INFO
robotframework_run_keyword_async.egg-info/SOURCES.txt
robotframework_run_keyword_async.egg-info/dependency_links.txt
robotframework_run_keyword_async.egg-info/requires.txt
robotframework_run_keyword_async.egg-info/top_level.txt
runKeywordAsync/__init__.py
runKeywordAsync/runKeywordAsync.py